yamlvault/__init__.py
yamlvault/ansible/loader.py
yamlvault/cli/__init__.py
yamlvault/cli/yamlvault.py
yamlvault/constants.py
yamlvault/django.py
yamlvault/environ_helper.py
yamlvault/exceptions.py
yamlvault/processor.py
yamlvault/settings.py
yamlvault/tags.py
yamlvault/utils.py
yamlvault-0.2.0.dist-info/METADATA
yamlvault-0.2.0.dist-info/WHEEL
yamlvault-0.2.0.dist-info/entry_points.txt
yamlvault-0.2.0.dist-info/RECORD
