Metadata-Version: 2.1
Name: yamlvault
Version: 0.2.0
Summary: A python module to store, encrypt and decrypt secrets variables in an encrypted yaml file using Ansible Vault encryption
Author: Dan Brosnan
Author-email: dpjbrosnan@gmail.com
Requires-Python: >=3.10,<4.0
Classifier: Programming Language :: Python :: 3
Classifier: Programming Language :: Python :: 3.10
Classifier: Programming Language :: Python :: 3.11
Classifier: Programming Language :: Python :: 3.12
Requires-Dist: ansible-vault (>=2.1.0,<3.0.0)
Requires-Dist: black (>=24.4.1,<25.0.0)
Requires-Dist: click (>=8.1.7,<9.0.0)
Requires-Dist: django (>=4.0.0,<5.0.0)
Requires-Dist: django-environ (>=0.11.2,<0.12.0)
Requires-Dist: pdbpp (>=0.10.3,<0.11.0)
Requires-Dist: pytest (>=6.2.5,<7.0.0)
Requires-Dist: ruamel-yaml (>=0.18.6,<0.19.0)
